odoo/addons/l10n_nl_tax_statement_icp/README.rst
odoo/addons/l10n_nl_tax_statement_icp/__init__.py
odoo/addons/l10n_nl_tax_statement_icp/__manifest__.py
odoo/addons/l10n_nl_tax_statement_icp/data/ir_config_parameter.xml
odoo/addons/l10n_nl_tax_statement_icp/i18n/l10n_nl_tax_statement_icp.pot
odoo/addons/l10n_nl_tax_statement_icp/i18n/nl.po
odoo/addons/l10n_nl_tax_statement_icp/models/__init__.py
odoo/addons/l10n_nl_tax_statement_icp/models/l10n_nl_vat_statement.py
odoo/addons/l10n_nl_tax_statement_icp/models/l10n_nl_vat_statement_icp_line.py
odoo/addons/l10n_nl_tax_statement_icp/readme/CONFIGURE.rst
odoo/addons/l10n_nl_tax_statement_icp/readme/CONTRIBUTORS.rst
odoo/addons/l10n_nl_tax_statement_icp/readme/DESCRIPTION.rst
odoo/addons/l10n_nl_tax_statement_icp/readme/ROADMAP.rst
odoo/addons/l10n_nl_tax_statement_icp/readme/USAGE.rst
odoo/addons/l10n_nl_tax_statement_icp/report/report_tax_statement.xml
odoo/addons/l10n_nl_tax_statement_icp/security/ir.model.access.csv
odoo/addons/l10n_nl_tax_statement_icp/static/description/icon.png
odoo/addons/l10n_nl_tax_statement_icp/static/description/index.html
odoo/addons/l10n_nl_tax_statement_icp/tests/__init__.py
odoo/addons/l10n_nl_tax_statement_icp/tests/test_l10n_nl_tax_statement_icp.py
odoo/addons/l10n_nl_tax_statement_icp/views/l10n_nl_vat_statement_view.xml
odoo/addons/l10n_nl_tax_statement_icp/views/report_tax_statement.xml
odoo12_addon_l10n_nl_tax_statement_icp-12.0.1.1.0.dist-info/METADATA
odoo12_addon_l10n_nl_tax_statement_icp-12.0.1.1.0.dist-info/WHEEL
odoo12_addon_l10n_nl_tax_statement_icp-12.0.1.1.0.dist-info/top_level.txt
odoo12_addon_l10n_nl_tax_statement_icp-12.0.1.1.0.dist-info/RECORD
